MANIFEST.in
requirements.txt
setup.cfg
setup.py
liquidnitrogen/__init__.py
liquidnitrogen/exceptions.py
liquidnitrogen/liquidnitrogen.py
liquidnitrogen.egg-info/PKG-INFO
liquidnitrogen.egg-info/SOURCES.txt
liquidnitrogen.egg-info/dependency_links.txt
liquidnitrogen.egg-info/pbr.json
liquidnitrogen.egg-info/requires.txt
liquidnitrogen.egg-info/top_level.txt