Metadata-Version: 1.1
Name: liquidnitrogen
Version: 0.0.0
Summary: freeze arbitrary Python things as immutables
Home-page: https://github.com/mcandre/liquidnitrogen
Author: Andrew Pennebaker
Author-email: andrew.pennebaker@gmail.com
License: FreeBSD
Download-URL: git@github.com:mcandre/liquidnitrogen.git
Platform: UNKNOWN
